d64py/Chain.py
d64py/Constants.py
d64py/D64Utility.py
d64py/DirEntry.py
d64py/DirHeader.py
d64py/DiskImage.py
d64py/DiskImageFactory.py
d64py/Exceptions.py
d64py/Geometry.py
d64py/GeosFileHeader.py
d64py/TrackSector.py
d64py/__init__.py
d64py/images/BOGEOS2.D64
d64py/images/COMAL0.14.D64
d64py/images/__init__.py
d64py/images/becker-basic.d64
d64py/images/geopublish-b.d64
d64py-3.2.0.dist-info/licenses/LICENSE
d64py-3.2.0.dist-info/METADATA
d64py-3.2.0.dist-info/WHEEL
d64py-3.2.0.dist-info/top_level.txt
d64py-3.2.0.dist-info/RECORD
