Metadata-Version: 2.4
Name: d64py
Version: 3.2.0
Summary: Cenbe's Commodore 64 Disk Image Library
Author-email: Glenn Holmer <cenbe@protonmail.com>
Project-URL: Repository, https://codeberg.org/Cenbe/d64py
Keywords: Commodore,GEOS
Classifier: Programming Language :: Python :: 3
Classifier: Development Status :: 5 - Production/Stable
Requires-Python: >=3.13
License-File: LICENSE
Requires-Dist: requests
Requires-Dist: importlib.metadata; python_version >= "3.13"
Dynamic: license-file
